COPYING
MANIFEST.in
README.rst
requirements.txt
setup.py
tasks.py
dedocs/conf.py
dedocs/.build/about.html
dedocs/.build/index.html
dedocs/.build/search.html
dedocs/.build/searchindex.js
dedocs/.build/_sources/about.rst.txt
dedocs/.build/_sources/index.rst.txt
dedocs/.build/_sources/basics/index.rst.txt
dedocs/.build/_sources/basics/intro.rst.txt
dedocs/.build/_sources/basics/schema.rst.txt
dedocs/.build/_sources/basics/settings.rst.txt
dedocs/.build/_sources/basics/suchen.rst.txt
dedocs/.build/_sources/bh/bank.rst.txt
dedocs/.build/_sources/bh/ekr.rst.txt
dedocs/.build/_sources/bh/index.rst.txt
dedocs/.build/_sources/bh/ledger.rst.txt
dedocs/.build/_sources/bh/vkr.rst.txt
dedocs/.build/_sources/changes/18.10.0.rst.txt
dedocs/.build/_sources/changes/18.11.0.rst.txt
dedocs/.build/_sources/changes/18.11.1.rst.txt
dedocs/.build/_sources/changes/18.12.0.rst.txt
dedocs/.build/_sources/changes/18.8.0.rst.txt
dedocs/.build/_sources/changes/19.1.0.rst.txt
dedocs/.build/_sources/changes/19.2.0.rst.txt
dedocs/.build/_sources/changes/coming.rst.txt
dedocs/.build/_sources/changes/index.rst.txt
dedocs/.build/_sources/em/index.rst.txt
dedocs/.build/_sources/em/patienten.rst.txt
dedocs/.build/_sources/sa/index.rst.txt
dedocs/.build/_sources/sa/users.rst.txt
dedocs/.build/_sources/th/akten.rst.txt
dedocs/.build/_sources/th/barzahlungen.rst.txt
dedocs/.build/_sources/th/cal.rst.txt
dedocs/.build/_sources/th/index.rst.txt
dedocs/.build/_sources/th/notes.rst.txt
dedocs/.build/_static/base-stemmer.js
dedocs/.build/_static/basic.css
dedocs/.build/_static/centeredlogo.css
dedocs/.build/_static/doctools.js
dedocs/.build/_static/documentation_options.js
dedocs/.build/_static/favicon-20140303.ico
dedocs/.build/_static/favicon-20140306.ico
dedocs/.build/_static/favicon.ico
dedocs/.build/_static/german-stemmer.js
dedocs/.build/_static/graphviz.css
dedocs/.build/_static/jquery-3.5.1.js
dedocs/.build/_static/jquery.js
dedocs/.build/_static/language_data.js
dedocs/.build/_static/linodocs.css
lino_tera.egg-info/PKG-INFO
lino_tera.egg-info/SOURCES.txt
lino_tera.egg-info/dependency_links.txt
lino_tera.egg-info/not-zip-safe
lino_tera.egg-info/requires.txt
lino_tera.egg-info/top_level.txt
