Metadata-Version: 2.1
Name: lino-tera
Version: 23.3.0
Summary: A Lino for managing therapeutic centres
Home-page: https://gitlab.com/lino-framework/tera
Author: Rumma & Ko Ltd
Author-email: info@lino-framework.org
License: UNKNOWN
Platform: UNKNOWN
Classifier: Programming Language :: Python
Classifier: Programming Language :: Python :: 3
Classifier: Development Status :: 4 - Beta
Classifier: Environment :: Web Environment
Classifier: Framework :: Django
Classifier: Intended Audience :: Developers
Classifier: Intended Audience :: System Administrators
Classifier: Intended Audience :: Information Technology
Classifier: Intended Audience :: Customer Service
Classifier: License :: OSI Approved :: GNU Affero General Public License v3
Classifier: Operating System :: OS Independent
License-File: COPYING
